philos/__init__.py
philos/organize_screenshots.py
philos/phile.py
philos/philesys.py
philos-0.1.0.dist-info/LICENSE.txt
philos-0.1.0.dist-info/METADATA
philos-0.1.0.dist-info/WHEEL
philos-0.1.0.dist-info/entry_points.txt
philos-0.1.0.dist-info/RECORD
