Metadata-Version: 2.3
Name: philos
Version: 0.1.0
Summary: A tool to organize screenshots.
License: MIT
Keywords: screenshot,organization
Author: Sidhart Krishnan
Author-email: sidhartkrishnan@gmail.com
Requires-Python: >=3.13,<4.0
Classifier: License :: OSI Approved :: MIT License
Classifier: Programming Language :: Python :: 3
Classifier: Programming Language :: Python :: 3.13
Requires-Dist: pillow
